olconv/__init__.py
olconv/__init__.pyi
olconv/compat.py
olconv/compat.pyi
olconv/conv_table.py
olconv/conv_table.pyi
olconv/olconv.py
olconv/olconv.pyi
olconv/py.typed
olconv-0.0.1.dist-info/METADATA
olconv-0.0.1.dist-info/WHEEL
olconv-0.0.1.dist-info/top_level.txt
olconv-0.0.1.dist-info/RECORD
